codewords_client/__init__.py
codewords_client/codewords_client.py
codewords_client/redis.py
codewords_client-0.4.0.dist-info/METADATA
codewords_client-0.4.0.dist-info/WHEEL
codewords_client-0.4.0.dist-info/top_level.txt
codewords_client-0.4.0.dist-info/RECORD
