Metadata-Version: 2.4
Name: codewords-client
Version: 0.4.0
Summary: Python client for CodeWords with auto-configured FastAPI integration.
Author-email: Osman Ramadan <osman@agemo.ai>
License-Expression: MIT
Requires-Python: >=3.11
Requires-Dist: httpx>=0.25.0
Requires-Dist: fastapi>=0.100.0
Requires-Dist: structlog>=23.0.0
Requires-Dist: pydantic>=2.0.0
Requires-Dist: uvicorn[standard]>=0.20.0
Requires-Dist: redis>=5.0.0
Provides-Extra: openai
Requires-Dist: openai>=1.0.0; extra == "openai"
Provides-Extra: anthropic
Requires-Dist: anthropic>=0.25.0; extra == "anthropic"
Provides-Extra: firecrawl
Requires-Dist: firecrawl>=1.0.0; extra == "firecrawl"
Provides-Extra: perplexityai
Requires-Dist: perplexityai>=1.0.0; extra == "perplexityai"
Provides-Extra: all
Requires-Dist: openai>=1.0.0; extra == "all"
Requires-Dist: anthropic>=0.25.0; extra == "all"
Requires-Dist: firecrawl>=1.0.0; extra == "all"
Requires-Dist: perplexityai>=1.0.0; extra == "all"
